planetary_system_stacker/__init__.py
planetary_system_stacker/align_frames.py
planetary_system_stacker/alignment_point_editor.py
planetary_system_stacker/alignment_point_editor_gui.py
planetary_system_stacker/alignment_points.py
planetary_system_stacker/configuration.py
planetary_system_stacker/configuration_editor.py
planetary_system_stacker/dark_flat_test.py
planetary_system_stacker/display_quickstart.py
planetary_system_stacker/exceptions.py
planetary_system_stacker/frame_selector.py
planetary_system_stacker/frame_selector_gui.py
planetary_system_stacker/frame_viewer.py
planetary_system_stacker/frame_viewer_gui.py
planetary_system_stacker/frames.py
planetary_system_stacker/frames_old.py
planetary_system_stacker/job_dialog.py
planetary_system_stacker/job_editor.py
planetary_system_stacker/main_gui.py
planetary_system_stacker/miscellaneous.py
planetary_system_stacker/parameter_configuration.py
planetary_system_stacker/planetary_system_stacker.py
planetary_system_stacker/postproc_editor.py
planetary_system_stacker/postproc_editor_gui.py
planetary_system_stacker/pss_console.py
planetary_system_stacker/quickstart_gui.py
planetary_system_stacker/rank_frames.py
planetary_system_stacker/rectangular_patch_editor.py
planetary_system_stacker/rectangular_patch_editor_gui.py
planetary_system_stacker/ser_parser.py
planetary_system_stacker/sharpening_layer_widget.py
planetary_system_stacker/shift_distribution_viewer.py
planetary_system_stacker/shift_distribution_viewer_gui.py
planetary_system_stacker/stack_frames.py
planetary_system_stacker/timer.py
planetary_system_stacker/version_manager_widget.py
planetary_system_stacker/workflow.py
planetary_system_stacker/Icons/PSS-Icon-64.ico
planetary_system_stacker/Icons/PSS-Icon-64.png
planetary_system_stacker/Icons/__init__.py
planetary_system_stacker-0.9.8.3.dist-info/METADATA
planetary_system_stacker-0.9.8.3.dist-info/WHEEL
planetary_system_stacker-0.9.8.3.dist-info/entry_points.txt
planetary_system_stacker-0.9.8.3.dist-info/top_level.txt
planetary_system_stacker-0.9.8.3.dist-info/RECORD
