Metadata-Version: 2.1
Name: planetary-system-stacker
Version: 0.9.8.3
Summary: PlanetarySystemStacker
Home-page: https://github.com/Rolf-Hempel/PlanetarySystemStacker
Author: Rolf Hempel
Author-email: rolf6419@gmx.de
License: UNKNOWN
Platform: UNKNOWN
Classifier: Programming Language :: Python :: 3
Classifier: Development Status :: 4 - Beta
Classifier: License :: OSI Approved :: GNU General Public License v3 (GPLv3)
Classifier: Operating System :: MacOS
Requires-Python: >=3.5
Requires-Dist: numpy (<1.23.0)
Requires-Dist: matplotlib
Requires-Dist: psutil
Requires-Dist: PyQt5 (>=5.15)
Requires-Dist: scipy
Requires-Dist: astropy
Requires-Dist: scikit-image
Requires-Dist: opencv-python-headless
